chalk/__init__.py
chalk/chalk.py
chalkx-0.2.dist-info/METADATA
chalkx-0.2.dist-info/WHEEL
chalkx-0.2.dist-info/top_level.txt
chalkx-0.2.dist-info/RECORD
