Metadata-Version: 2.1
Name: chalkx
Version: 0.2
Summary: A simple package to change text color in CMD prompt using ANSI escape codes
Home-page: https://github.com/triple7inc/chalk
Author: triple7inc
License: MIT
Classifier: Programming Language :: Python :: 3
Classifier: License :: OSI Approved :: MIT License
Classifier: Operating System :: OS Independent
Requires-Python: >=2.0
